dasida/__init__.py
dasida/scripts.py
dasida/aws/__init__.py
dasida/aws/common.py
dasida/aws/s3.py
dasida/aws/secretsmanager.py
dasida/aws/sqs.py
dasida/aws/ssm.py
dasida/docker/__init__.py
dasida/docker/docker.py
dasida-2023.7.4.dist-info/LICENSE
dasida-2023.7.4.dist-info/METADATA
dasida-2023.7.4.dist-info/WHEEL
dasida-2023.7.4.dist-info/entry_points.txt
dasida-2023.7.4.dist-info/top_level.txt
dasida-2023.7.4.dist-info/RECORD
