Metadata-Version: 2.1
Name: dasida
Version: 2023.7.4
Summary: dasida
Author: Woojin Cho
Author-email: w.cho@cj.net
Requires-Python: >=3.8
License-File: LICENSE
Requires-Dist: aioboto3
Requires-Dist: boto3
Requires-Dist: click
Requires-Dist: click-loglevel
Requires-Dist: tabulate
Requires-Dist: pendulum
Requires-Dist: pydantic
Requires-Dist: rich
Requires-Dist: InquirerPy
